CHANGES.txt
LICENSE.txt
MANIFEST.in
README.txt
setup.py
Pysa.egg-info/PKG-INFO
Pysa.egg-info/SOURCES.txt
Pysa.egg-info/dependency_links.txt
Pysa.egg-info/top_level.txt
bin/pysa
bin/pysa2puppet
examples/.gitignore
examples/filters.addition
examples/filters.discard
examples/filters.replace
examples/filters.update
examples/pysa.cfg
pysa/__init__.py
pysa/config.py
pysa/dependencies.py
pysa/exception.py
pysa/madeira.py
pysa/output.py
pysa/preprocessing.py
pysa/tools.py
pysa/filter/__init__.py
pysa/filter/filter.py
pysa/filter/parser.py
pysa/puppet/__init__.py
pysa/puppet/build.py
pysa/puppet/converter.py
pysa/puppet/objects.py
pysa/salt/__init__.py
pysa/salt/build.py
pysa/salt/converter.py
pysa/salt/objects.py
pysa/scanner/__init__.py
pysa/scanner/scanner_handler.py
pysa/scanner/actions/__init__.py
pysa/scanner/actions/base.py
pysa/scanner/actions/cron.py
pysa/scanner/actions/file.py
pysa/scanner/actions/gem.py
pysa/scanner/actions/group.py
pysa/scanner/actions/host.py
pysa/scanner/actions/mount.py
pysa/scanner/actions/npm.py
pysa/scanner/actions/package.py
pysa/scanner/actions/php.py
pysa/scanner/actions/process.py
pysa/scanner/actions/pypi.py
pysa/scanner/actions/repository.py
pysa/scanner/actions/service.py
pysa/scanner/actions/source.py
pysa/scanner/actions/sshkey.py
pysa/scanner/actions/user.py
pysa/scanner/actions/utils.py
pysa/scanner/object/__init__.py
pysa/scanner/object/cron.py
pysa/scanner/object/file.py
pysa/scanner/object/group.py
pysa/scanner/object/host.py
pysa/scanner/object/mount.py
pysa/scanner/object/object_base.py
pysa/scanner/object/package.py
pysa/scanner/object/process.py
pysa/scanner/object/repository.py
pysa/scanner/object/service.py
pysa/scanner/object/source.py
pysa/scanner/object/sshkey.py
pysa/scanner/object/user.py