Metadata-Version: 1.0
Name: Pysa
Version: 0.3b4
Summary: Reverse your Servers Configuration
Home-page: http://madeiracloud.github.io/pysa/
Author: Thibault BRONCHAIN - MadeiraCloud Ltd.
Author-email: pysa@mc2.io
License: LICENSE.txt
Download-URL: http://pypi.python.org/packages/source/P/Pysa/Pysa-0.3b4.tar.gz
Platform: UNKNOWN
Classifier: Development Status :: 4 - Beta
Classifier: Environment :: Console
Classifier: Intended Audience :: System Administrators
Classifier: License :: OSI Approved :: GNU General Public License v3 or later (GPLv3+)
Classifier: Operating System :: POSIX :: Linux
Classifier: Topic :: System
